{"is_source_file": true, "format": "JavaScript (React JSX)", "description": "React component for a modal dialog used to create or edit notes. It manages focus trapping, accessibility labels, and handles user interactions for submitting or cancelling the note.", "external_files": ["react", "react (useEffect, useRef, useState)"], "external_methods": ["React.useEffect", "React.useRef", "React.useState"], "published": [], "classes": [], "methods": [{"name": "NoteModal({ isOpen, mode = 'create', initialValue, onCancel, onSubmit, isSubmitting })", "description": "Functional React component rendering a modal for creating/editing notes, with internal state management and event handling.", "scope": "", "scopeKind": ""}], "calls": ["document.addEventListener", "document.removeEventListener"], "search-terms": ["NoteModal", "React JSX modal", "create/edit note dialog", "accessibility modal React", "useRef focus trap"], "state": 2, "file_id": 18, "knowledge_revision": 36, "git_revision": "", "ctags": [{"_type": "tag", "name": "10", "path": "/home/kavia/workspace/code-generation/note-management-system-162739-162748/notes_frontend/src/components/NoteModal.js", "pattern": "/^              rows={10}$/", "language": "JavaScript", "kind": "field", "scope": "NoteModal.rows", "scopeKind": "class"}, {"_type": "tag", "name": "200", "path": "/home/kavia/workspace/code-generation/note-management-system-162739-162748/notes_frontend/src/components/NoteModal.js", "pattern": "/^              maxLength={200}$/", "language": "JavaScript", "kind": "field", "scope": "NoteModal.maxLength", "scopeKind": "class"}, {"_type": "tag", "name": "NoteModal", "path": "/home/kavia/workspace/code-generation/note-management-system-162739-162748/notes_frontend/src/components/NoteModal.js", "pattern": "/^export default function NoteModal({ isOpen, mode = 'create', initialValue, onCancel, onSubmit, i/", "language": "JavaScript", "kind": "function", "signature": "({ isOpen, mode = 'create', initialValue, onCancel, onSubmit, isSubmitting })"}, {"_type": "tag", "name": "content", "path": "/home/kavia/workspace/code-generation/note-management-system-162739-162748/notes_frontend/src/components/NoteModal.js", "pattern": "/^              value={content}$/", "language": "JavaScript", "kind": "field", "scope": "NoteModal.value", "scopeKind": "class"}, {"_type": "tag", "name": "dialogRef", "path": "/home/kavia/workspace/code-generation/note-management-system-162739-162748/notes_frontend/src/components/NoteModal.js", "pattern": "/^        ref={dialogRef}$/", "language": "JavaScript", "kind": "field", "scope": "NoteModal.ref", "scopeKind": "class"}, {"_type": "tag", "name": "title", "path": "/home/kavia/workspace/code-generation/note-management-system-162739-162748/notes_frontend/src/components/NoteModal.js", "pattern": "/^              value={title}$/", "language": "JavaScript", "kind": "field", "scope": "NoteModal.value", "scopeKind": "class"}, {"_type": "tag", "name": "titleRef", "path": "/home/kavia/workspace/code-generation/note-management-system-162739-162748/notes_frontend/src/components/NoteModal.js", "pattern": "/^              ref={titleRef}$/", "language": "JavaScript", "kind": "field", "scope": "NoteModal.ref", "scopeKind": "class"}], "hash": "aa5572e7acdeff0de36a6c29415d28c9", "format-version": 4, "code-base-name": "notes_frontend", "filename": "notes_frontend/src/components/NoteModal.js", "fields": [{"name": "rows={10}", "scope": "NoteModal.rows", "scopeKind": "class", "description": "unavailable"}, {"name": "maxLength={200}", "scope": "NoteModal.maxLength", "scopeKind": "class", "description": "unavailable"}, {"name": "value={content}", "scope": "NoteModal.value", "scopeKind": "class", "description": "unavailable"}, {"name": "ref={dialogRef}", "scope": "NoteModal.ref", "scopeKind": "class", "description": "unavailable"}, {"name": "value={title}", "scope": "NoteModal.value", "scopeKind": "class", "description": "unavailable"}, {"name": "ref={titleRef}", "scope": "NoteModal.ref", "scopeKind": "class", "description": "unavailable"}], "revision_history": [{"36": ""}]}